uncertainty_engine_resource_client/__init__.py
uncertainty_engine_resource_client/api/__init__.py
uncertainty_engine_resource_client/api/account_records_api.py
uncertainty_engine_resource_client/api/auth_api.py
uncertainty_engine_resource_client/api/default_api.py
uncertainty_engine_resource_client/api/project_records_api.py
uncertainty_engine_resource_client/api/resources_api.py
uncertainty_engine_resource_client/api/templates_api.py
uncertainty_engine_resource_client/api/workflows_api.py
uncertainty_engine_resource_client/api_client.py
uncertainty_engine_resource_client/api_response.py
uncertainty_engine_resource_client/configuration.py
uncertainty_engine_resource_client/exceptions.py
uncertainty_engine_resource_client/models/__init__.py
uncertainty_engine_resource_client/models/account_record_input.py
uncertainty_engine_resource_client/models/account_record_output.py
uncertainty_engine_resource_client/models/account_response.py
uncertainty_engine_resource_client/models/get_account_record_projects_response.py
uncertainty_engine_resource_client/models/get_resource_records_response.py
uncertainty_engine_resource_client/models/get_resource_version_records_response.py
uncertainty_engine_resource_client/models/get_resource_version_response.py
uncertainty_engine_resource_client/models/get_workflow_records_response.py
uncertainty_engine_resource_client/models/get_workflow_template_records_response.py
uncertainty_engine_resource_client/models/get_workflow_version_records_response.py
uncertainty_engine_resource_client/models/http_validation_error.py
uncertainty_engine_resource_client/models/patch_project_record_name_request.py
uncertainty_engine_resource_client/models/post_account_record_request.py
uncertainty_engine_resource_client/models/post_project_record_request.py
uncertainty_engine_resource_client/models/post_resource_record_request.py
uncertainty_engine_resource_client/models/post_resource_version_request.py
uncertainty_engine_resource_client-0.2.0.dist-info/METADATA
uncertainty_engine_resource_client-0.2.0.dist-info/WHEEL
uncertainty_engine_resource_client-0.2.0.dist-info/RECORD
