Metadata-Version: 2.3
Name: uncertainty-engine-resource-client
Version: 0.2.0
Summary: 
Author: Jasper Cantwell
Author-email: jasper@digilab.ai
Requires-Python: <4, >=3.10
Classifier: Programming Language :: Python :: 3
Classifier: Programming Language :: Python :: 3.10
Classifier: Programming Language :: Python :: 3.11
Classifier: Programming Language :: Python :: 3.12
Classifier: Programming Language :: Python :: 3.13
Requires-Dist: aiohttp (>=3.11.18,<4.0.0)
Requires-Dist: aiohttp-retry (>=2.9.1,<3.0.0)
Requires-Dist: pydantic (>=2.11.3,<3.0.0)
Requires-Dist: python-dateutil (>=2.9.0.post0,<3.0.0)
Requires-Dist: urllib3 (>=2.4.0,<3.0.0)
